voice2brief-0.1.2.dist-info/METADATA
voice2brief-0.1.2.dist-info/WHEEL
voice2brief-0.1.2.dist-info/entry_points.txt
voice2brief/__init__.py
voice2brief/cli.py
voice2brief/processor.py
voice2brief-0.1.2.dist-info/RECORD
