Metadata-Version: 2.1
Name: voice2brief
Version: 0.1.2
Summary: Convert voice memos into actionable briefs and meeting notes using AI
Author-Email: coccoinomane <coccoinomane@gmail.com>
License: MIT
Project-URL: homepage, https://github.com/coccoinomane/voice2brief
Project-URL: repository, https://github.com/coccoinomane/voice2brief
Requires-Python: >=3.13
Requires-Dist: openai>=1.61.1
Requires-Dist: anthropic>=0.45.2
Requires-Dist: pydub>=0.25.1
Requires-Dist: audioop-lts>=0.2.1
